README.md
setup.cfg
setup.py
instagram_stalker/__init__.py
instagram_stalker/app.py
instagram_stalker/constants.py
instagram_stalker.egg-info/PKG-INFO
instagram_stalker.egg-info/SOURCES.txt
instagram_stalker.egg-info/dependency_links.txt
instagram_stalker.egg-info/entry_points.txt
instagram_stalker.egg-info/not-zip-safe
instagram_stalker.egg-info/requires.txt
instagram_stalker.egg-info/top_level.txt