Metadata-Version: 1.0
Name: instagram-stalker
Version: 0.2.0
Summary: Observes given instagram account and notify when he makes his account public.
Home-page: http://github.com/pkacprzak/instagram-stalker
Author: Pawel Kacprzak
Author-email: pawel.kacprzak.89@gmail.com
License: Public domain
Keywords: instagram,scraper,stalker,observer,photos
Platform: UNKNOWN
